Metadata-Version: 2.1
Name: python-switch
Version: 1.0
Summary: Python Switch Like JavaScript Switch Statement
Home-page: https://github.com/isacolak/python_switch
Author: isacolak
Author-email: isacolak04@gmail.com
License: MIT
Download-URL: https://github.com/isacolak/python_switch/archive/python_switch_v_1.tar.gz
Keywords: switch,python js switch,python javascript switch,python switch
Platform: UNKNOWN
Classifier: Development Status :: 3 - Alpha
Classifier: Intended Audience :: Developers
Classifier: Topic :: Software Development :: Libraries :: Python Modules
Classifier: License :: OSI Approved :: MIT License
Classifier: Programming Language :: Python :: 3.6
Classifier: Programming Language :: Python :: 3.7
Classifier: Programming Language :: Python :: 3.8
Classifier: Programming Language :: Python :: 3.9
